simplemc/__init__.py
simplemc/profile.py
simplemc-0.0.3.dist-info/LICENSE
simplemc-0.0.3.dist-info/METADATA
simplemc-0.0.3.dist-info/WHEEL
simplemc-0.0.3.dist-info/top_level.txt
simplemc-0.0.3.dist-info/RECORD
