Metadata-Version: 2.1
Name: simplemc
Version: 0.0.3
Summary: A simple API for the game Minecraft.
Home-page: https://github.com/elflanded/simplemc
Author: Elflanded
Author-email: Elflanded@gmail.com
License: UNKNOWN
Platform: UNKNOWN
Classifier: Programming Language :: Python :: 3
Classifier: License :: OSI Approved :: MIT License
Classifier: Operating System :: OS Independent
Requires-Python: >=3.6
